graphlearning/__init__.py
graphlearning/active_learning.py
graphlearning/cextensions.cpython-39-darwin.so
graphlearning/clustering.py
graphlearning/datasets.py
graphlearning/graph.py
graphlearning/ssl.py
graphlearning/trainsets.py
graphlearning/utils.py
graphlearning/weightmatrix.py
graphlearning-1.7.5.dist-info/licenses/LICENSE
graphlearning-1.7.5.dist-info/METADATA
graphlearning-1.7.5.dist-info/WHEEL
graphlearning-1.7.5.dist-info/top_level.txt
graphlearning-1.7.5.dist-info/RECORD
