Metadata-Version: 2.4
Name: graphlearning
Version: 1.7.5
Summary: Python package for graph-based clustering and semi-supervised learning
Author-email: Jeff Calder <jwcalder@umn.edu>
License: MIT
Project-URL: Homepage, https://github.com/jwcalder/GraphLearning
Project-URL: Bug Tracker, https://github.com/jwcalder/GraphLearning/issues
Classifier: Programming Language :: Python :: 3
Classifier: License :: OSI Approved :: MIT License
Classifier: Operating System :: OS Independent
Requires-Python: >=3.6
License-File: LICENSE
Requires-Dist: numpy
Requires-Dist: scipy
Requires-Dist: scikit-learn
Requires-Dist: matplotlib
Dynamic: license-file
